ChineseErrorCorrector/__init__.py
ChineseErrorCorrector/config.py
ChineseErrorCorrector/dat.py
ChineseErrorCorrector/utils.py
ChineseErrorCorrector/data/dat_data/README.md
ChineseErrorCorrector/data/dat_data/confuse_obj_v.json
ChineseErrorCorrector/data/dat_data/confuse_sub_v.json
ChineseErrorCorrector/data/dat_data/confuse_v_obj.json
ChineseErrorCorrector/data/dat_data/confuse_v_sub.json
ChineseErrorCorrector/data/dat_data/new_cofuse_set.txt
ChineseErrorCorrector/data/dat_data/token_set.txt
ChineseErrorCorrector/pre_model/ltp_tiny/added_tokens.json
ChineseErrorCorrector/pre_model/ltp_tiny/config.json
ChineseErrorCorrector/pre_model/ltp_tiny/pytorch_model.bin
ChineseErrorCorrector/pre_model/ltp_tiny/special_tokens_map.json
ChineseErrorCorrector/pre_model/ltp_tiny/tokenizer.json
ChineseErrorCorrector/pre_model/ltp_tiny/tokenizer_config.json
ChineseErrorCorrector/pre_model/ltp_tiny/vocab.txt
ChineseErrorCorrector-1.6.0.dist-info/LICENSE
ChineseErrorCorrector-1.6.0.dist-info/METADATA
ChineseErrorCorrector-1.6.0.dist-info/WHEEL
ChineseErrorCorrector-1.6.0.dist-info/top_level.txt
ChineseErrorCorrector-1.6.0.dist-info/RECORD
